flipperzero_protobuf/__init__.py
flipperzero_protobuf/cli_helpers.py
flipperzero_protobuf/flipper_app.py
flipperzero_protobuf/flipper_base.py
flipperzero_protobuf/flipper_desktop.py
flipperzero_protobuf/flipper_gpio.py
flipperzero_protobuf/flipper_gui.py
flipperzero_protobuf/flipper_property.py
flipperzero_protobuf/flipper_proto.py
flipperzero_protobuf/flipper_storage.py
flipperzero_protobuf/flipper_sys.py
flipperzero_protobuf/version.py
flipperzero_protobuf/flipperCmd/__init__.py
flipperzero_protobuf/flipperCmd/__main__.py
flipperzero_protobuf/flipperCmd/cmd_complete.py
flipperzero_protobuf/flipperCmd/flipperCmd.py
flipperzero_protobuf/flipperCmd/flipperzero_cmd.py
flipperzero_protobuf/flipperzero_protobuf_compiled/__init__.py
flipperzero_protobuf/flipperzero_protobuf_compiled/__init__.pyi
flipperzero_protobuf/flipperzero_protobuf_compiled/application_pb2.py
flipperzero_protobuf/flipperzero_protobuf_compiled/desktop_pb2.py
flipperzero_protobuf/flipperzero_protobuf_compiled/flipper_pb2.py
flipperzero_protobuf/flipperzero_protobuf_compiled/gpio_pb2.py
flipperzero_protobuf/flipperzero_protobuf_compiled/gui_pb2.py
flipperzero_protobuf/flipperzero_protobuf_compiled/property_pb2.py
flipperzero_protobuf/flipperzero_protobuf_compiled/storage_pb2.py
flipperzero_protobuf/flipperzero_protobuf_compiled/system_pb2.py
flipperzero_protobuf-0.1.20221108.dist-info/METADATA
flipperzero_protobuf-0.1.20221108.dist-info/WHEEL
flipperzero_protobuf-0.1.20221108.dist-info/entry_points.txt
flipperzero_protobuf-0.1.20221108.dist-info/top_level.txt
flipperzero_protobuf-0.1.20221108.dist-info/RECORD
