Metadata-Version: 2.1
Name: flipperzero_protobuf
Version: 0.1.20221108
Summary: Python bindings for Flipper Zero protobuf protocol
Home-page: https://github.com/evilpete/flipperzero_protobuf_py
Author: Flipper & Community
Author-email: flipper devices <hello@flipperzero.one>, peter shipley <peter.shipley@gmail.com>
License: BSD 3-Clause License
Project-URL: Homepage, https://github.com/oltenxyz/flipperzero_protobuf_py
Project-URL: Bug Tracker, https://github.com/oltenxyz/flipperzero_protobuf_py/issues
Keywords: flipperzero,protobuf
Classifier: Programming Language :: Python :: 3
Classifier: License :: OSI Approved :: BSD License
Classifier: Operating System :: OS Independent
Requires-Python: >=3
Requires-Dist: numpy ==1.22.3
Requires-Dist: protobuf ==3.20.2
Requires-Dist: pyserial
